arithmeticapp/app.py
ArithmeticOperations-1.0.0.dist-info/LICENSE
ArithmeticOperations-1.0.0.dist-info/METADATA
ArithmeticOperations-1.0.0.dist-info/WHEEL
ArithmeticOperations-1.0.0.dist-info/top_level.txt
ArithmeticOperations-1.0.0.dist-info/RECORD
