Metadata-Version: 2.1
Name: ArithmeticOperations
Version: 1.0.0
Summary: Basic Calculator App
Home-page: https://github.com/Jhansi-27/Calculator
Author: JhansiRani
Author-email: jhansi.rc26@gmail.com
License: MIT
Platform: UNKNOWN
Classifier: License :: OSI Approved :: MIT License
Classifier: Programming Language :: Python :: 3.7
Requires-Dist: requests
